sanic_prometheus/__init__.py
sanic_prometheus/endpoint.py
sanic_prometheus/exceptions.py
sanic_prometheus/metrics.py
sanic_prometheus-0.2.1.dist-info/LICENSE
sanic_prometheus-0.2.1.dist-info/METADATA
sanic_prometheus-0.2.1.dist-info/WHEEL
sanic_prometheus-0.2.1.dist-info/top_level.txt
sanic_prometheus-0.2.1.dist-info/RECORD
