Metadata-Version: 2.1
Name: sanic-prometheus
Version: 0.2.1
Summary: Exposes Prometheus monitoring metrics of Sanic apps.
Home-page: http://github.com/dkruchinin/sanic-prometheus
Author: Dan Kruchinin
Author-email: dan.kruchinin@gmail.com
License: MIT
Keywords: sanic prometheus monitoring
Platform: any
Classifier: Intended Audience :: Developers
Classifier: Development Status :: 3 - Alpha
Classifier: License :: OSI Approved :: MIT License
Classifier: Operating System :: OS Independent
Classifier: Environment :: Web Environment
Classifier: Topic :: System :: Monitoring
Classifier: Topic :: Internet :: WWW/HTTP :: Dynamic Content
Classifier: Topic :: Software Development :: Libraries :: Python Modules
Classifier: Programming Language :: Python :: 3.6
Classifier: Programming Language :: Python :: 3.7
Requires-Dist: sanic (>=18.12)
Requires-Dist: prometheus-client (~=0.7.1)
Requires-Dist: psutil (>=5.2.0)
